vintage_vectors/__init__.py
vintage_vectors/main.py
vintage_vectors-1.1.dist-info/METADATA
vintage_vectors-1.1.dist-info/WHEEL
vintage_vectors-1.1.dist-info/top_level.txt
vintage_vectors-1.1.dist-info/RECORD
