Metadata-Version: 2.1
Name: vintage_vectors
Version: 1.1
Requires-Dist: torch
